Counter_10.v
module Counter_10(clk, Add, Reset, Cnt_10);
    input   clk;
    input   Add;
    input   Reset;
    output  Cnt_10;

    reg[3:0]    C;

    initial
    begin
        C = 0;
    end

    assign  Cnt_10 = (C == 9) ? 1'b1 : 1'b0;

    always @(posedge clk) 
    begin
        @(negedge Add)      //negtive edge trigger Add
        C <= C + 1;
    end

    always @(posedge clk) 
    begin
        @(posedge Reset)    //positive edge trigger Reset
        C <= 0;
    end

endmodule // Counter10

Register.v
module Register(Sensor, Reset, En);
    input   Sensor;
    input   Reset;
    output reg  En;

    initial 
    begin
        En = 1'b0;
    end


    always @(negedge Sensor) //negtive edge trigger sensor
    begin
        En <= 1'b1;
    end

    always @(posedge Reset) //positive edge trigger reset
    begin
        En <= 1'b0;
    end

endmodule // Register

Timer_2.v
module Timer_2(clk, En_T2, R_TR, Timeout2);
    input   clk;
    input   En_T2;
    input   R_TR;
    output  Timeout2;

    reg[1:0]    counter;

    assign Timeout2 = (counter == 2) ? 1'b1 : 1'b0;
    
    always @(clk or En_T2) 
    begin
        if (En_T2 == 1'b1)
        begin
            @(posedge clk)
            counter <= counter + 1;
        end
    end

    always @(posedge R_TR)       //positive edge trigger reset
    begin
        counter <= 2'b00;
    end


endmodule // Timer2

Timer_1.v
module Timer_1(clk, En_T1, R_TR, Timeout1);
    input   clk;
    input   En_T1;
    input   R_TR;
    output  Timeout1;

    reg[3:0]    counter;

    assign Timeout1 = (counter == 10) ? 1'b1 : 1'b0;
    
    always @(clk or En_T1) 
    begin
        if (En_T1 == 1'b1)
        begin
            @(posedge clk)
            counter <= counter + 1;
        end
    end

    always @(posedge R_TR)      //positive edge trigger reset
    begin
        counter <= 4'b0000;
    end


endmodule // Timer1

Main_control.v
module Main_control(
    input   clk,
    input   Mov_l, Mov_r, Mov_f, Mov_b,
    input   Grab,
    input   Touch,
    input   Top,
    input   Origin,
    input   En_claw,
    input   Timeout1,
    input   Timeout2,
    input   Cnt_10,
    input   Success,
    output reg  Return,
    output reg  Down,
    output reg  Rise,
    output reg  Open,
    output reg  Tight,
    output reg  Loose,
    output reg  Release,
    output  En_T1,
    output  En_T2,
    output  Add,
    output  R_C,
    output  R_TR,
    output  Un_claw
);
    //control signal    
    reg     Un_claw;     //鎖住搖桿（使Move訊號無效）
    reg     En_T1;       //啟動timer1
    reg     En_T2;       //啟動timer2
    reg     Add;         //使counter+1
    reg     R_C;         //使counter歸零
    reg     R_TR;        //重設Timer1、Timer2、Register1、Register2

    reg[3:0]    State;
    reg[3:0]    Nextstate;


    initial
    begin
        State = 0;
    end
    


       
    always @(*) 
    begin : main_control
        case (State)
            0:
                    begin
                        En_T1 = 1'b0;
                        En_T2 = 1'b0;
                        Un_claw = 1'b0;
                        Add = 1'b0;
                        R_C = 1'b1;
                        R_TR = 1'b1;
                        Return = 1'b0;
                        Down = 1'b0;
                        Rise = 1'b0;
                        Open = 1'b0;
                        Tight = 1'b0;
                        Loose = 1'b0;
                        Release = 1'b0; 
                        if (En_claw == 1'b1)
                        begin
                            Nextstate = 1;
                        end
                        else
                        begin
                            Nextstate = 0;
                        end
                    end
            1:
                    begin
                        R_TR = 1'b0;
                        if (Mov_l || Mov_r || Mov_f || Mov_b)
                        begin
                            Nextstate = 2;
                        end
                        else
                        begin
                            Nextstate = 1;
                        end
                    end
            2:
                    begin
                        En_T1 = 1'b1;
                        if (Grab == 1'b1 || Timeout1 == 1'b1)
                        begin
                            Nextstate = 3; 
                        end 
                        else
                        begin
                            Nextstate = 2;
                        end
                    end
            3:
                    begin
                        En_T1 = 1'b0;
                        Un_claw = 1'b1;
                        Down = 1'b1;
                        Open = 1'b1;
                        if (Touch == 1'b1 && Cnt_10 == 1'b0)
                        begin
                            Nextstate = 4;
                        end
                        else if (Touch == 1'b1 && Cnt_10 == 1'b1)
                        begin
                            Nextstate = 5;
                        end
                    end
            4:
                    begin
                        Loose = 1'b1;
                        Down = 1'b0;
                        Open = 1'b0;
                        Nextstate = 6; 
                    end
            5:
                    begin
                        Tight = 1'b1;
                        Down = 1'b0;
                        Open = 1'b0; 
                        Nextstate = 7;
                    end
            6:
                    begin
                        Loose = 1'b1;
                        Rise = 1'b1;
                        if (Top == 1'b1)
                        begin
                            Nextstate = 8;
                        end
                        else
                        begin
                            Nextstate = 6; 
                        end 
                    end
            7:
                    begin
                        Tight = 1'b1;
                        Rise = 1'b1;
                        if (Top == 1'b1)
                        begin
                            Nextstate = 9;
                        end
                        else
                        begin
                            Nextstate = 7; 
                        end 
                    end
            8:
                    begin
                        Rise = 1'b0;
                        Loose = 1'b1;
                        Return = 1'b1;
                        if (Origin == 1'b1)
                        begin
                            Nextstate = 10;
                        end
                        else
                        begin
                            Nextstate = 8;
                        end 
                    end
            9:
                    begin
                        Rise = 1'b0;
                        Tight = 1'b1;
                        Return = 1'b1;
                        if (Origin == 1'b1)
                        begin
                            Nextstate = 10;
                        end
                        else
                        begin
                            Nextstate = 9;
                        end 
                    end
            10:
                    begin
                        Return = 1'b0;
                        Loose = 1'b0;
                        Tight = 1'b0;
                        Release = 1'b1;
                        En_T2 = 1'b1;
                        if (Timeout2 == 1'b1 && Cnt_10 == 1'b1)
                        begin
                            R_C = 1'b0;
                            Nextstate = 0;
                        end
                        else if (Timeout2 == 1'b1 && Cnt_10 == 1'b0 && Success == 1'b1)
                        begin
                           R_C = 1'b0;
                           Nextstate = 0; 
                        end
                        else if (Timeout2 == 1'b1 && Cnt_10 == 1'b0 && Success == 1'b0)
                        begin
                           Add = 1'b1;
                           Nextstate = 0; 
                        end
                        else
                        begin
                            Nextstate = 10;
                        end
                    end       
            default: 
                    begin
                        Nextstate = 0;
                    end
        endcase 
    end

    always @(posedge clk) 
    begin
        State <= Nextstate;
    end

    



endmodule // Claw_machine

Claw_Machine.v
module Claw_Machine(
    input   clk,
    input   Coin,
    input   Mov_l, Mov_r, Mov_f, Mov_b,
    input   Grab,
    input   Touch,
    input   Top,
    input   Origin,
    input   Drop,
    output  Claw_l, Claw_r, Claw_f, Claw_b,
    output   Return,
    output   Down,
    output   Rise,
    output   Open,
    output   Tight,
    output   Loose,
    output   Release
);

    wire   En_claw;     //允許操控搖桿（使Move訊號有效）
    wire   Timeout1;    //當timer1超過10clock
    wire   Timeout2;    //timer超過2clock
    wire   Cnt_10;      //當counter數到10
    wire   Success; 
    wire    En_T1;
    wire    En_T2;
    wire    Add;
    wire    R_C;
    wire    R_TR;
    wire    Un_claw;

    assign Claw_l = (En_claw & ~Un_claw) ? Mov_l : 1'b0;
    assign Claw_r = (En_claw & ~Un_claw) ? Mov_r : 1'b0;
    assign Claw_f = (En_claw & ~Un_claw) ? Mov_f : 1'b0;
    assign Claw_b = (En_claw & ~Un_claw) ? Mov_b : 1'b0;


    Main_control    Main_control(.clk(clk), .Mov_l(Mov_l), .Mov_r(Mov_r), .Mov_f(Mov_f), .Mov_b(Mov_b), 
                                .Grab(Grab), .Touch(Touch), .Top(Top), .Origin(Origin),
                                .En_claw(En_claw), .Timeout1(Timeout1), .Timeout2(Timeout2), .Cnt_10(Cnt_10), .Success(Success),  
                                .Return(Return), .Down(Down), .Rise(Rise), .Open(Open), 
                                .Tight(Tight), .Loose(Loose), .Release(Release), .En_T1(En_T1), .En_T2(En_T2), .Add(Add), .R_C(R_C), .R_TR(R_TR),
                                .Un_claw(Un_claw));
                                
    Timer_1     T1(clk, En_T1, R_TR, Timeout1);
    Timer_2     T2(clk, En_T2, R_TR, Timeout2);
    Register    R1(.Sensor(Coin), .Reset(R_TR), .En(En_claw));
    Register    R2(.Sensor(Drop), .Reset(R_TR), .En(Success));
    Counter_10  C(clk, Add, R_C, Cnt_10);
endmodule

t_Claw_Machine.v
`timescale 1ns/100ps
module t_Claw_Machine;
    reg   clk;
    reg   Coin;
    reg   Mov_l, Mov_r, Mov_f, Mov_b;
    reg   Grab;
    reg   Touch;
    reg   Top;
    reg   Origin;
    reg   Drop;
    wire    Claw_l, Claw_r, Claw_f, Claw_b;
    wire    Return;
    wire    Down;
    wire    Rise;
    wire    Open;
    wire    Tight;
    wire    Loose;
    wire    Release;
    integer i;
    parameter N = 11;


    initial
    begin
        $dumpfile("Claw_Machine.vcd");
        $dumpvars;
    end

    always
    begin
        #10 clk = ~clk;
    end

    initial
    begin
        clk = 1'b0;
        Coin = 1'b1;
        Grab = 1'b0;
        Drop = 1'b1;
        Mov_l = 1'b0;
        Mov_r = 1'b0;
        Mov_f = 1'b0;
        Mov_b = 1'b0;
        Touch = 1'b0;
        Top = 1'b0;
        Origin = 1'b0;
    end

    always @(posedge clk) 
    begin
        //第一次：測Register1, Grab按鈕
        #30 Coin = 1'b0;
        #20 Mov_l = 1'b0; Mov_r = 1'b0; Mov_f = 1'b0; Mov_b = 1'b1; Coin = 1;
        #20 Mov_l = 1'b0; Mov_r = 1'b1; Mov_f = 1'b0; Mov_b = 1'b0;
        #20 Grab = 1'b1; Mov_r = 1'b0;
        @(posedge Down)
        #10 Grab = 1'b0;
        #40 Touch = 1'b1;
        @(posedge clk)
        Touch = 1'b0;
        #60 Top = 1'b1;
        @(posedge clk)
        @(negedge clk)
        Top = 1'b0;
        #50 Origin = 1'b1;
        #20 Origin = 1'b0;
        #20 Mov_l = 1'b1; Mov_r = 1'b0; Mov_f = 1'b0; Mov_b = 1'b0;
        #20 Mov_l = 1'b0; Mov_r = 1'b1; Mov_f = 1'b0; Mov_b = 1'b0;
        #20 Mov_l = 1'b0; Mov_r = 1'b0; Mov_f = 1'b1; Mov_b = 1'b0;
        #20 Mov_l = 1'b0; Mov_r = 1'b0; Mov_f = 1'b0; Mov_b = 1'b1;
        //第二次：測Timer1, Timer2, Register2, counter_10
        #20 Coin = 1'b0;
        #20 Mov_l = 1'b0; Mov_r = 1'b1; Mov_f = 1'b0; Mov_b = 1'b0; Coin = 1'b1; 
        #80 Mov_l = 1'b0; Mov_r = 1'b0; Mov_f = 1'b0; Mov_b = 1'b1;
        #40 Mov_l = 1'b0; Mov_r = 1'b0; Mov_f = 1'b1; Mov_b = 1'b0;
        #20 Mov_l = 1'b1; Mov_r = 1'b0; Mov_f = 1'b0; Mov_b = 1'b0;
        @(posedge Down)
        Mov_f = 1'b0;
        #50 Touch = 1'b1;
        @(posedge clk)
        Touch = 1'b0;
        #50 Top = 1'b1;
        @(posedge clk)
        Top = 1'b0;
        #50 Origin = 1'b1;
        #20 Drop = 1'b0; Origin = 1'b0;
        #20 Drop = 1'b1;
        //第三次到第十三次：測保夾、Counter_10重置
        for (i = 1; i <= N; i = i+1) 
        begin
            #100 Coin = 1'b0;
            #20 Mov_l = 1'b0; Mov_r = 1'b1; Mov_f = 1'b0; Mov_b = 1'b0; Coin = 1;
            #20 Mov_r = 1'b0;
            #20 Grab = 1'b1;
            @(posedge Down)
            Grab = 1'b0;
            #50 Touch = 1'b1;
            @(posedge clk)
            Touch = 1'b0;
            #50 Top = 1'b1;
            @(posedge clk)
            Top = 1'b0;
            #50 Origin = 1'b1;
            #20 Origin = 1'b0;
        end
    end


    initial #5000 $finish;

    Claw_Machine    M(clk, Coin, Mov_l, Mov_r, Mov_f, Mov_b, 
                    Grab, Touch, Top, Origin, Drop, 
                    Claw_l, Claw_r, Claw_f, Claw_b, 
                    Return, Down, Rise, Open, 
                    Tight, Loose, Release);

endmodule // t_Claw_Machine

Claw_Machine.vcd
$date
	Mon Dec 30 20:25:01 2019
$end
$version
	Icarus Verilog
$end
$timescale
	100ps
$end
$scope module t_Claw_Machine $end
$var wire 1 ! Tight $end
$var wire 1 " Rise $end
$var wire 1 # Return $end
$var wire 1 $ Release $end
$var wire 1 % Open $end
$var wire 1 & Loose $end
$var wire 1 ' Down $end
$var wire 1 ( Claw_r $end
$var wire 1 ) Claw_l $end
$var wire 1 * Claw_f $end
$var wire 1 + Claw_b $end
$var reg 1 , Coin $end
$var reg 1 - Drop $end
$var reg 1 . Grab $end
$var reg 1 / Mov_b $end
$var reg 1 0 Mov_f $end
$var reg 1 1 Mov_l $end
$var reg 1 2 Mov_r $end
$var reg 1 3 Origin $end
$var reg 1 4 Top $end
$var reg 1 5 Touch $end
$var reg 1 6 clk $end
$var integer 32 7 i [31:0] $end
$scope module M $end
$var wire 1 , Coin $end
$var wire 1 - Drop $end
$var wire 1 . Grab $end
$var wire 1 / Mov_b $end
$var wire 1 0 Mov_f $end
$var wire 1 1 Mov_l $end
$var wire 1 2 Mov_r $end
$var wire 1 3 Origin $end
$var wire 1 4 Top $end
$var wire 1 5 Touch $end
$var wire 1 6 clk $end
$var wire 1 8 Un_claw $end
$var wire 1 9 Timeout2 $end
$var wire 1 : Timeout1 $end
$var wire 1 ! Tight $end
$var wire 1 ; Success $end
$var wire 1 " Rise $end
$var wire 1 # Return $end
$var wire 1 $ Release $end
$var wire 1 < R_TR $end
$var wire 1 = R_C $end
$var wire 1 % Open $end
$var wire 1 & Loose $end
$var wire 1 > En_claw $end
$var wire 1 ? En_T2 $end
$var wire 1 @ En_T1 $end
$var wire 1 ' Down $end
$var wire 1 A Cnt_10 $end
$var wire 1 ( Claw_r $end
$var wire 1 ) Claw_l $end
$var wire 1 * Claw_f $end
$var wire 1 + Claw_b $end
$var wire 1 B Add $end
$scope module C $end
$var wire 1 6 clk $end
$var wire 1 = Reset $end
$var wire 1 A Cnt_10 $end
$var wire 1 B Add $end
$var reg 4 C C [3:0] $end
$upscope $end
$scope module Main_control $end
$var wire 1 A Cnt_10 $end
$var wire 1 . Grab $end
$var wire 1 / Mov_b $end
$var wire 1 0 Mov_f $end
$var wire 1 1 Mov_l $end
$var wire 1 2 Mov_r $end
$var wire 1 3 Origin $end
$var wire 1 4 Top $end
$var wire 1 5 Touch $end
$var wire 1 6 clk $end
$var wire 1 9 Timeout2 $end
$var wire 1 : Timeout1 $end
$var wire 1 ; Success $end
$var wire 1 > En_claw $end
$var reg 1 B Add $end
$var reg 1 ' Down $end
$var reg 1 @ En_T1 $end
$var reg 1 ? En_T2 $end
$var reg 1 & Loose $end
$var reg 4 D Nextstate [3:0] $end
$var reg 1 % Open $end
$var reg 1 = R_C $end
$var reg 1 < R_TR $end
$var reg 1 $ Release $end
$var reg 1 # Return $end
$var reg 1 " Rise $end
$var reg 4 E State [3:0] $end
$var reg 1 ! Tight $end
$var reg 1 8 Un_claw $end
$scope begin main_control $end
$upscope $end
$upscope $end
$scope module R1 $end
$var wire 1 < Reset $end
$var wire 1 , Sensor $end
$var reg 1 > En $end
$upscope $end
$scope module R2 $end
$var wire 1 < Reset $end
$var wire 1 - Sensor $end
$var reg 1 ; En $end
$upscope $end
$scope module T1 $end
$var wire 1 @ En_T1 $end
$var wire 1 < R_TR $end
$var wire 1 6 clk $end
$var wire 1 : Timeout1 $end
$var reg 4 F counter [3:0] $end
$upscope $end
$scope module T2 $end
$var wire 1 ? En_T2 $end
$var wire 1 < R_TR $end
$var wire 1 6 clk $end
$var wire 1 9 Timeout2 $end
$var reg 2 G counter [1:0] $end
$upscope $end
$upscope $end
$upscope $end
$enddefinitions $end
#0
$dumpvars
b0 G
b0 F
b0 E
b0 D
b0 C
0B
0A
0@
0?
0>
1=
1<
0;
0:
09
08
bx 7
06
05
04
03
02
01
00
0/
0.
1-
1,
0+
0*
0)
0(
0'
0&
0%
0$
0#
0"
0!
$end
#100
16
#200
06
#300
16
#400
b1 D
1>
06
0,
#500
0<
b1 E
16
#600
1+
b10 D
06
1,
1/
#700
1@
b10 E
16
#800
0+
1(
06
0/
12
#900
b1 F
16
#1000
0(
b11 D
06
02
1.
#1100
1%
1'
18
0@
b11 E
b10 F
16
#1200
0.
06
#1300
16
#1400
06
#1500
16
#1600
b100 D
06
15
#1700
b110 D
0%
0'
1&
b100 E
05
16
#1800
06
#1900
1"
b110 E
16
#2000
06
#2100
16
#2200
06
#2300
1#
0"
b1000 E
b1000 D
16
14
#2400
04
06
#2500
16
#2600
06
#2700
16
#2800
06
#2900
1?
1$
0&
0#
b1010 E
b1010 D
16
13
#3000
06
#3100
b1 G
16
03
#3200
06
#3300
b0 D
1B
19
b10 G
16
11
#3400
06
#3500
0>
b0 F
b1 C
0(
b0 D
0$
1<
0B
08
0?
09
b0 E
b0 G
16
12
01
#3600
06
#3700
16
10
02
#3800
06
#3900
16
1/
00
#4000
06
#4100
1+
b1 D
1>
16
0,
#4200
06
#4300
b10 D
0<
b1 E
0+
1(
16
1,
0/
12
#4400
06
#4500
1@
b10 E
16
#4600
06
#4700
b1 F
16
#4800
06
#4900
b10 F
16
#5000
06
#5100
b11 F
1+
0(
16
1/
02
#5200
06
#5300
b100 F
16
#5400
06
#5500
b101 F
0+
1*
16
0/
10
#5600
06
#5700
b110 F
0*
1)
16
00
11
#5800
06
#5900
b111 F
16
#6000
06
#6100
b1000 F
16
#6200
06
#6300
b1001 F
16
#6400
06
#6500
b11 D
1:
b1010 F
16
#6600
06
#6700
0)
1%
1'
18
0@
0:
b11 E
b1011 F
16
#6800
06
#6900
16
#7000
06
#7100
16
#7200
b100 D
06
15
#7300
b110 D
0%
0'
1&
b100 E
05
16
#7400
06
#7500
1"
b110 E
16
#7600
06
#7700
16
#7800
b1000 D
06
14
#7900
1#
0"
b1000 E
b1000 D
04
16
#8000
06
#8100
16
#8200
06
#8300
16
#8400
b1010 D
06
13
#8500
1?
1$
0&
0#
b1010 E
16
#8600
1;
06
03
0-
#8700
b1 G
16
#8800
06
b1 7
1-
#8900
b0 D
0=
19
b10 G
16
#9000
06
#9100
b0 F
0>
0;
b0 C
0)
b0 D
0$
1<
1=
08
0?
09
b0 E
b0 G
16
#9200
06
#9300
16
#9400
06
#9500
16
#9600
06
#9700
16
#9800
1)
b1 D
1>
06
0,
#9900
b10 D
0<
b1 E
16
#10000
1(
0)
06
1,
12
01
#10100
1@
b10 E
16
#10200
0(
06
02
#10300
b1 F
16
#10400
b11 D
06
1.
#10500
0.
1%
1'
18
0@
b11 E
b10 F
16
#10600
06
#10700
16
#10800
06
#10900
16
#11000
b100 D
06
15
#11100
b110 D
0%
0'
1&
b100 E
05
16
#11200
06
#11300
1"
b110 E
16
#11400
06
#11500
16
#11600
b1000 D
06
14
#11700
1#
0"
b1000 E
b1000 D
04
16
#11800
06
#11900
16
#12000
06
#12100
16
#12200
b1010 D
06
13
#12300
1?
1$
0&
0#
b1010 E
16
#12400
06
b10 7
03
#12500
b1 G
16
#12600
06
#12700
b0 D
1B
19
b10 G
16
#12800
06
#12900
0>
b0 F
b1 C
b0 D
0$
1<
0B
08
0?
09
b0 E
b0 G
16
#13000
06
#13100
16
#13200
06
#13300
16
#13400
b1 D
1>
06
0,
#13500
0<
b1 E
16
#13600
1(
b10 D
06
1,
12
#13700
1@
b10 E
16
#13800
0(
06
02
#13900
b1 F
16
#14000
b11 D
06
1.
#14100
0.
1%
1'
18
0@
b11 E
b10 F
16
#14200
06
#14300
16
#14400
06
#14500
16
#14600
b100 D
06
15
#14700
b110 D
0%
0'
1&
b100 E
05
16
#14800
06
#14900
1"
b110 E
16
#15000
06
#15100
16
#15200
b1000 D
06
14
#15300
1#
0"
b1000 E
b1000 D
04
16
#15400
06
#15500
16
#15600
06
#15700
16
#15800
b1010 D
06
13
#15900
1?
1$
0&
0#
b1010 E
16
#16000
06
b11 7
03
#16100
b1 G
16
#16200
06
#16300
b0 D
1B
19
b10 G
16
#16400
06
#16500
b0 F
0>
b10 C
b0 D
0$
1<
0B
08
0?
09
b0 E
b0 G
16
#16600
06
#16700
16
#16800
06
#16900
16
#17000
b1 D
1>
06
0,
#17100
0<
b1 E
16
#17200
1(
b10 D
06
1,
12
#17300
1@
b10 E
16
#17400
0(
06
02
#17500
b1 F
16
#17600
b11 D
06
1.
#17700
0.
1%
1'
18
0@
b11 E
b10 F
16
#17800
06
#17900
16
#18000
06
#18100
16
#18200
b100 D
06
15
#18300
b110 D
0%
0'
1&
b100 E
05
16
#18400
06
#18500
1"
b110 E
16
#18600
06
#18700
16
#18800
b1000 D
06
14
#18900
1#
0"
b1000 E
b1000 D
04
16
#19000
06
#19100
16
#19200
06
#19300
16
#19400
b1010 D
06
13
#19500
1?
1$
0&
0#
b1010 E
16
#19600
06
b100 7
03
#19700
b1 G
16
#19800
06
#19900
b0 D
1B
19
b10 G
16
#20000
06
#20100
0>
b0 F
b11 C
b0 D
0$
1<
0B
08
0?
09
b0 E
b0 G
16
#20200
06
#20300
16
#20400
06
#20500
16
#20600
b1 D
1>
06
0,
#20700
0<
b1 E
16
#20800
1(
b10 D
06
1,
12
#20900
1@
b10 E
16
#21000
0(
06
02
#21100
b1 F
16
#21200
b11 D
06
1.
#21300
0.
1%
1'
18
0@
b11 E
b10 F
16
#21400
06
#21500
16
#21600
06
#21700
16
#21800
b100 D
06
15
#21900
b110 D
0%
0'
1&
b100 E
05
16
#22000
06
#22100
1"
b110 E
16
#22200
06
#22300
16
#22400
b1000 D
06
14
#22500
1#
0"
b1000 E
b1000 D
04
16
#22600
06
#22700
16
#22800
06
#22900
16
#23000
b1010 D
06
13
#23100
1?
1$
0&
0#
b1010 E
16
#23200
06
b101 7
03
#23300
b1 G
16
#23400
06
#23500
b0 D
1B
19
b10 G
16
#23600
06
#23700
b0 F
0>
b100 C
b0 D
0$
1<
0B
08
0?
09
b0 E
b0 G
16
#23800
06
#23900
16
#24000
06
#24100
16
#24200
b1 D
1>
06
0,
#24300
0<
b1 E
16
#24400
1(
b10 D
06
1,
12
#24500
1@
b10 E
16
#24600
0(
06
02
#24700
b1 F
16
#24800
b11 D
06
1.
#24900
0.
1%
1'
18
0@
b11 E
b10 F
16
#25000
06
#25100
16
#25200
06
#25300
16
#25400
b100 D
06
15
#25500
b110 D
0%
0'
1&
b100 E
05
16
#25600
06
#25700
1"
b110 E
16
#25800
06
#25900
16
#26000
b1000 D
06
14
#26100
1#
0"
b1000 E
b1000 D
04
16
#26200
06
#26300
16
#26400
06
#26500
16
#26600
b1010 D
06
13
#26700
1?
1$
0&
0#
b1010 E
16
#26800
06
b110 7
03
#26900
b1 G
16
#27000
06
#27100
b0 D
1B
19
b10 G
16
#27200
06
#27300
0>
b0 F
b101 C
b0 D
0$
1<
0B
08
0?
09
b0 E
b0 G
16
#27400
06
#27500
16
#27600
06
#27700
16
#27800
b1 D
1>
06
0,
#27900
0<
b1 E
16
#28000
1(
b10 D
06
1,
12
#28100
1@
b10 E
16
#28200
0(
06
02
#28300
b1 F
16
#28400
b11 D
06
1.
#28500
0.
1%
1'
18
0@
b11 E
b10 F
16
#28600
06
#28700
16
#28800
06
#28900
16
#29000
b100 D
06
15
#29100
b110 D
0%
0'
1&
b100 E
05
16
#29200
06
#29300
1"
b110 E
16
#29400
06
#29500
16
#29600
b1000 D
06
14
#29700
1#
0"
b1000 E
b1000 D
04
16
#29800
06
#29900
16
#30000
06
#30100
16
#30200
b1010 D
06
13
#30300
1?
1$
0&
0#
b1010 E
16
#30400
06
b111 7
03
#30500
b1 G
16
#30600
06
#30700
b0 D
1B
19
b10 G
16
#30800
06
#30900
b0 F
0>
b110 C
b0 D
0$
1<
0B
08
0?
09
b0 E
b0 G
16
#31000
06
#31100
16
#31200
06
#31300
16
#31400
b1 D
1>
06
0,
#31500
0<
b1 E
16
#31600
1(
b10 D
06
1,
12
#31700
1@
b10 E
16
#31800
0(
06
02
#31900
b1 F
16
#32000
b11 D
06
1.
#32100
0.
1%
1'
18
0@
b11 E
b10 F
16
#32200
06
#32300
16
#32400
06
#32500
16
#32600
b100 D
06
15
#32700
b110 D
0%
0'
1&
b100 E
05
16
#32800
06
#32900
1"
b110 E
16
#33000
06
#33100
16
#33200
b1000 D
06
14
#33300
1#
0"
b1000 E
b1000 D
04
16
#33400
06
#33500
16
#33600
06
#33700
16
#33800
b1010 D
06
13
#33900
1?
1$
0&
0#
b1010 E
16
#34000
06
b1000 7
03
#34100
b1 G
16
#34200
06
#34300
b0 D
1B
19
b10 G
16
#34400
06
#34500
0>
b0 F
b111 C
b0 D
0$
1<
0B
08
0?
09
b0 E
b0 G
16
#34600
06
#34700
16
#34800
06
#34900
16
#35000
b1 D
1>
06
0,
#35100
0<
b1 E
16
#35200
1(
b10 D
06
1,
12
#35300
1@
b10 E
16
#35400
0(
06
02
#35500
b1 F
16
#35600
b11 D
06
1.
#35700
0.
1%
1'
18
0@
b11 E
b10 F
16
#35800
06
#35900
16
#36000
06
#36100
16
#36200
b100 D
06
15
#36300
b110 D
0%
0'
1&
b100 E
05
16
#36400
06
#36500
1"
b110 E
16
#36600
06
#36700
16
#36800
b1000 D
06
14
#36900
1#
0"
b1000 E
b1000 D
04
16
#37000
06
#37100
16
#37200
06
#37300
16
#37400
b1010 D
06
13
#37500
1?
1$
0&
0#
b1010 E
16
#37600
06
b1001 7
03
#37700
b1 G
16
#37800
06
#37900
b0 D
1B
19
b10 G
16
#38000
06
#38100
b0 F
0>
b1000 C
b0 D
0$
1<
0B
08
0?
09
b0 E
b0 G
16
#38200
06
#38300
16
#38400
06
#38500
16
#38600
b1 D
1>
06
0,
#38700
0<
b1 E
16
#38800
1(
b10 D
06
1,
12
#38900
1@
b10 E
16
#39000
0(
06
02
#39100
b1 F
16
#39200
b11 D
06
1.
#39300
0.
1%
1'
18
0@
b11 E
b10 F
16
#39400
06
#39500
16
#39600
06
#39700
16
#39800
b100 D
06
15
#39900
b110 D
0%
0'
1&
b100 E
05
16
#40000
06
#40100
1"
b110 E
16
#40200
06
#40300
16
#40400
b1000 D
06
14
#40500
1#
0"
b1000 E
b1000 D
04
16
#40600
06
#40700
16
#40800
06
#40900
16
#41000
b1010 D
06
13
#41100
1?
1$
0&
0#
b1010 E
16
#41200
06
b1010 7
03
#41300
b1 G
16
#41400
06
#41500
b0 D
1B
19
b10 G
16
#41600
06
#41700
1A
0>
b0 F
b1001 C
b0 D
0$
1<
0B
08
0?
09
b0 E
b0 G
16
#41800
06
#41900
16
#42000
06
#42100
16
#42200
b1 D
1>
06
0,
#42300
0<
b1 E
16
#42400
1(
b10 D
06
1,
12
#42500
1@
b10 E
16
#42600
0(
06
02
#42700
b1 F
16
#42800
b11 D
06
1.
#42900
0.
1%
1'
18
0@
b11 E
b10 F
16
#43000
06
#43100
16
#43200
06
#43300
16
#43400
b101 D
06
15
#43500
b111 D
0%
0'
1!
b101 E
05
16
#43600
06
#43700
1"
b111 E
16
#43800
06
#43900
16
#44000
b1001 D
06
14
#44100
1#
0"
b1001 E
b1001 D
04
16
#44200
06
#44300
16
#44400
06
#44500
16
#44600
b1010 D
06
13
#44700
1?
1$
0!
0#
b1010 E
16
#44800
06
b1011 7
03
#44900
b1 G
16
#45000
06
#45100
b0 D
0=
19
b10 G
16
#45200
06
#45300
0A
b0 F
0>
b0 C
b0 D
0$
1<
1=
08
0?
09
b0 E
b0 G
16
#45400
06
#45500
16
#45600
06
#45700
16
#45800
b1 D
1>
06
0,
#45900
0<
b1 E
16
#46000
1(
b10 D
06
1,
12
#46100
1@
b10 E
16
#46200
0(
06
02
#46300
b1 F
16
#46400
b11 D
06
1.
#46500
0.
1%
1'
18
0@
b11 E
b10 F
16
#46600
06
#46700
16
#46800
06
#46900
16
#47000
b100 D
06
15
#47100
b110 D
0%
0'
1&
b100 E
05
16
#47200
06
#47300
1"
b110 E
16
#47400
06
#47500
16
#47600
b1000 D
06
14
#47700
1#
0"
b1000 E
b1000 D
04
16
#47800
06
#47900
16
#48000
06
#48100
16
#48200
b1010 D
06
13
#48300
1?
1$
0&
0#
b1010 E
16
#48400
06
b1100 7
03
#48500
b1 G
16
#48600
06
#48700
b0 D
1B
19
b10 G
16
#48800
06
0,
#48900
0>
b0 F
b1 C
b0 D
0$
1<
0B
08
0?
09
b0 E
b0 G
16
#49000
06
1,
1/
#49100
16
#49200
06
0/
12
#49300
16
#49400
06
02
1.
